<?xml version="1.0" encoding="UTF-8"?><record_update table="sp_instance">
    <sp_instance action="DELETE">
        <active>true</active>
        <class_name/>
        <color>default</color>
        <css/>
        <glyph/>
        <id/>
        <order>2</order>
        <roles/>
        <short_description/>
        <size>md</size>
        <sp_column display_value="1">7895cfb62f808a1052232e5df699b60e</sp_column>
        <sp_widget display_value="Relevant for you">6cc836d0dbf700500c209493db961914</sp_widget>
        <sys_class_name>sp_instance</sys_class_name>
        <sys_created_by>admin</sys_created_by>
        <sys_created_on>2024-02-03 07:54:11</sys_created_on>
        <sys_id>3495cfb62f808a1052232e5df699b611</sys_id>
        <sys_mod_count>14</sys_mod_count>
        <sys_name>HR Requests</sys_name>
        <sys_package display_value="Human Resource" source="x_1022175_hr">1980ab752f87f11052232e5df699b6c1</sys_package>
        <sys_policy/>
        <sys_scope display_value="Human Resource">1980ab752f87f11052232e5df699b6c1</sys_scope>
        <sys_update_name>sp_instance_3495cfb62f808a1052232e5df699b611</sys_update_name>
        <sys_updated_by>admin</sys_updated_by>
        <sys_updated_on>2024-02-08 22:13:35</sys_updated_on>
        <title>HR Requests</title>
        <url/>
        <widget_parameters><![CDATA[{
	"user_prediction_count": {
		"value": null,
		"displayValue": ""
	},
	"recent_activity_cut_off_in_days": {
		"value": null,
		"displayValue": ""
	},
	"title": {
		"value": "HR Requests",
		"displayValue": "HR Requests"
	},
	"limit": {
		"value": 5,
		"displayValue": "5"
	},
	"category": {
		"value": "catalog",
		"displayValue": "Catalog"
	},
	"list_type": {
		"value": "Simple List",
		"displayValue": "Simple List"
	},
	"card_behaviour": {
		"value": "wrap",
		"displayValue": "Wrap"
	},
	"load_config": {
		"value": "sync",
		"displayValue": "Synchronous"
	},
	"show_empty_state": {
		"value": "false",
		"displayValue": "false"
	}
}]]></widget_parameters>
    </sp_instance>
    <sys_translated_text action="DELETE" query="documentkey=3495cfb62f808a1052232e5df699b611"/>
    <sys_update_version action="INSERT_OR_UPDATE">
        <action>DELETE</action>
        <application display_value="Human Resource">1980ab752f87f11052232e5df699b6c1</application>
        <file_path/>
        <instance_id>60cecf3adbc8081452dd2f17d496199a</instance_id>
        <instance_name>dev93894</instance_name>
        <name>sp_instance_3495cfb62f808a1052232e5df699b611</name>
        <payload>&lt;?xml version="1.0" encoding="UTF-8"?&gt;&lt;record_update table="sp_instance"&gt;&lt;sp_instance action="INSERT_OR_UPDATE"&gt;&lt;active&gt;true&lt;/active&gt;&lt;class_name/&gt;&lt;color&gt;default&lt;/color&gt;&lt;css/&gt;&lt;glyph/&gt;&lt;id/&gt;&lt;order&gt;2&lt;/order&gt;&lt;roles/&gt;&lt;short_description/&gt;&lt;size&gt;md&lt;/size&gt;&lt;sp_column display_value="1"&gt;7895cfb62f808a1052232e5df699b60e&lt;/sp_column&gt;&lt;sp_widget display_value="Relevant for you"&gt;6cc836d0dbf700500c209493db961914&lt;/sp_widget&gt;&lt;sys_class_name&gt;sp_instance&lt;/sys_class_name&gt;&lt;sys_created_by&gt;admin&lt;/sys_created_by&gt;&lt;sys_created_on&gt;2024-02-03 07:54:11&lt;/sys_created_on&gt;&lt;sys_id&gt;3495cfb62f808a1052232e5df699b611&lt;/sys_id&gt;&lt;sys_mod_count&gt;14&lt;/sys_mod_count&gt;&lt;sys_name&gt;HR Requests&lt;/sys_name&gt;&lt;sys_package display_value="Human Resource" source="x_1022175_hr"&gt;1980ab752f87f11052232e5df699b6c1&lt;/sys_package&gt;&lt;sys_policy/&gt;&lt;sys_scope display_value="Human Resource"&gt;1980ab752f87f11052232e5df699b6c1&lt;/sys_scope&gt;&lt;sys_update_name&gt;sp_instance_3495cfb62f808a1052232e5df699b611&lt;/sys_update_name&gt;&lt;sys_updated_by&gt;admin&lt;/sys_updated_by&gt;&lt;sys_updated_on&gt;2024-02-08 22:13:35&lt;/sys_updated_on&gt;&lt;title&gt;HR Requests&lt;/title&gt;&lt;url/&gt;&lt;widget_parameters&gt;&lt;![CDATA[{
	"user_prediction_count": {
		"value": null,
		"displayValue": ""
	},
	"recent_activity_cut_off_in_days": {
		"value": null,
		"displayValue": ""
	},
	"title": {
		"value": "HR Requests",
		"displayValue": "HR Requests"
	},
	"limit": {
		"value": 5,
		"displayValue": "5"
	},
	"category": {
		"value": "catalog",
		"displayValue": "Catalog"
	},
	"list_type": {
		"value": "Simple List",
		"displayValue": "Simple List"
	},
	"card_behaviour": {
		"value": "wrap",
		"displayValue": "Wrap"
	},
	"load_config": {
		"value": "sync",
		"displayValue": "Synchronous"
	},
	"show_empty_state": {
		"value": "false",
		"displayValue": "false"
	}
}]]&gt;&lt;/widget_parameters&gt;&lt;/sp_instance&gt;&lt;sys_translated_text action="delete_multiple" query="documentkey=3495cfb62f808a1052232e5df699b611"/&gt;&lt;/record_update&gt;</payload>
        <payload_hash>-1221796065</payload_hash>
        <record_name>HR Requests</record_name>
        <reverted_from/>
        <source>f7dfe2712fc8461052232e5df699b667</source>
        <source_table>sys_update_set</source_table>
        <state>previous</state>
        <sys_created_by>admin</sys_created_by>
        <sys_created_on>2024-02-08 22:13:36</sys_created_on>
        <sys_id>a63a7b282f50825052232e5df699b6e7</sys_id>
        <sys_mod_count>0</sys_mod_count>
        <sys_recorded_at>18d8ac88ee40000001</sys_recorded_at>
        <sys_updated_by>admin</sys_updated_by>
        <sys_updated_on>2024-02-08 22:13:36</sys_updated_on>
        <type>Instance</type>
        <update_guid>ae3a7b28195082507b5135bf4a52efe6</update_guid>
        <update_guid_history>ae3a7b28195082507b5135bf4a52efe6:-1221796065,dc5937e40650825005e46b676483c624:-1383958145,10293fe4ed5082506aa871d40e427d02:2062404255,da19bbe41a50825061aa8c6e8bd0b3ff:645740702,94e96acb9a80ca10b40c4b6dccba9253:-1825936114,34d9e6cb7580ca1083c8f087ddbaa9af:-1916894513,27b966cb9480ca108eee4f11888d32bb:-1825936114,4cb926cb4b80ca10a57fda1b30f72da9:-1916894513,57696e8b3380ca10f0fe448f34cd187b:-2007852912,8409a28b5580ca103a2ba1c54d15cf4d:-1825936114,9946a687fc80ca107198041212d75194:-2117973518,7af566879a80ca103a274d11125ae1cf:1155766067,45156e07a680ca1065f89baf77dc166d:-2117973518,86501a4f8100ca101add49e675039f0a:-2104339763,fc95cfb695808a10fb8ea19e99d1f012:-658961179</update_guid_history>
    </sys_update_version>
    <sys_metadata_delete action="INSERT_OR_UPDATE">
        <sys_audit_delete display_value="HR Requests">8d9a3b682f50825052232e5df699b6e1</sys_audit_delete>
        <sys_class_name>sys_metadata_delete</sys_class_name>
        <sys_created_by>admin</sys_created_by>
        <sys_created_on>2024-02-08 22:15:08</sys_created_on>
        <sys_db_object display_value="" name="sp_instance">sp_instance</sys_db_object>
        <sys_id>11a5feb644224a588fa5db6c1ba5ddb9</sys_id>
        <sys_metadata>3495cfb62f808a1052232e5df699b611</sys_metadata>
        <sys_mod_count>0</sys_mod_count>
        <sys_name>HR Requests</sys_name>
        <sys_package display_value="Human Resource" source="x_1022175_hr">1980ab752f87f11052232e5df699b6c1</sys_package>
        <sys_parent/>
        <sys_policy/>
        <sys_scope display_value="Human Resource">1980ab752f87f11052232e5df699b6c1</sys_scope>
        <sys_scope_delete display_value="">17665fce484249118462a12012e01369</sys_scope_delete>
        <sys_update_name>sp_instance_3495cfb62f808a1052232e5df699b611</sys_update_name>
        <sys_update_version display_value="sp_instance_3495cfb62f808a1052232e5df699b611">a63a7b282f50825052232e5df699b6e7</sys_update_version>
        <sys_updated_by>admin</sys_updated_by>
        <sys_updated_on>2024-02-08 22:15:08</sys_updated_on>
    </sys_metadata_delete>
</record_update>
